Metadata-Version: 2.1
Name: xymath
Version: 0.3.1
Summary: A GUI and API that creates, documents and explores y=f(x) curve fits
Home-page: http://xymath.readthedocs.org/en/latest/
Download-URL: https://github.com/sonofeft/XYmath
Author: Charlie Taylor
Author-email: charlietaylor@users.sourceforge.net
License: GPL-3
Keywords: xymath setuptools development
Platform: any
Classifier: Development Status :: 4 - Beta
Classifier: Operating System :: OS Independent
Classifier: Intended Audience :: Developers
Classifier: Intended Audience :: End Users/Desktop
Classifier: Topic :: Software Development :: Build Tools
Classifier: License :: OSI Approved :: GNU General Public License v3 (GPLv3)
Classifier: Programming Language :: Python :: 2
Classifier: Programming Language :: Python :: 2.7
License-File: LICENSE.txt
License-File: AUTHORS.rst
Requires-Dist: mock
Requires-Dist: future
Requires-Dist: coverage
Requires-Dist: numpy
Requires-Dist: numexpr
Requires-Dist: scipy
Requires-Dist: pillow
Requires-Dist: matplotlib
Provides-Extra: dev
Requires-Dist: check-manifest ; extra == 'dev'
Provides-Extra: test
Requires-Dist: coverage ; extra == 'test'
